{
  "globalNote": "",
  "parts": {
    "snake_head.png": {
      "note": "",
      "overlayPath": "D:\\Projects\\Game_Arrows\\.local-data\\skin-gen\\jobs\\mnddm86q-b0jsj8\\input\\snake_head_overlay.png"
    },
    "snake_head_curious.png": {
      "note": ""
    },
    "snake_head_sleepy.png": {
      "note": ""
    },
    "snake_head_surprised.png": {
      "note": ""
    },
    "snake_seg_a.png": {
      "note": ""
    },
    "snake_seg_b.png": {
      "note": ""
    },
    "snake_tail_base.png": {
      "note": ""
    },
    "snake_tail_tip.png": {
      "note": ""
    }
  }
}
